{
  "profile_id": "soas-professor-elisa-van-waeyenberge",
  "name": "Professor Elisa Van Waeyenberge",
  "title": "College of Social Sciences | Dean of College | Department of Economics | Professor in Development Economics",
  "department": "Department of Economics",
  "expertise_topics": [
    "Principal Investigator",
    "Trajectories of Infrastructure Financing",
    "ESRC-NIESR funded via Rebuilding Macroeconomics",
    "together with Kate Bayliss and Benjamin Bowles.Co-Investigator on a GCRF",
    "ESRC Strategic Network entitled Equalities in Public Private Partnership (EQUIPPPS)International financial institutions",
    "alternative macroeconomic policy",
    "infrastructure financing",
    "public private partnerships",
    "Housing policy in developing countries.Co-Investigator in a FP7 funded programme entitled Financialisati"
  ],
  "biography": "Van Waeyenberge, Elisa, Bargawi, Hannah and McKinley, Terry (2011). Penang: (Third World Network)",
  "research_interests": "Principal Investigator; Trajectories of Infrastructure Financing; ESRC-NIESR funded via Rebuilding Macroeconomics; together with Kate Bayliss and Benjamin Bowles.Co-Investigator on a GCRF; ESRC Strategic Network entitled Equalities in Public Private Partnership (EQUIPPPS)International financial institutions; alternative macroeconomic policy; infrastructure financing; public private partnerships; Housing policy in developing countries.Co-Investigator in a FP7 funded programme entitled Financialisati",
  "publications": "https://www.soas.ac.uk/; https://www.soas.ac.uk/about; https://www.soas.ac.uk/about/colleges/college-social-sciences; https://www.soas.ac.uk/about/colleges/college-social-sciences/department-economics; https://www.soas.ac.uk/about/james-naughton; https://www.soas.ac.uk/about/joe-sam; https://www.soas.ac.uk/about/maria-jose-romero; https://www.soas.ac.uk/ramp-university-network; https://www.soas.ac.uk/research/trajectories-infrastructure-financing-and-macroeconomic-policies-practice; https://www.soas.ac.uk/study/find-course/msc-economics; mailto:ew23@soas.ac.uk",
  "languages": [],
  "source_url": "https://www.soas.ac.uk/about/elisa-van-waeyenberge",
  "last_checked": "2026-02-21",
  "content_hash": "7fbb2b5a718c71b3dd9fec5241b3e8167005feabda0ffd78ec11cd0ff4240749",
  "email_contact": "ew23@soas.ac.uk"
}