{
  "profile_id": "soas-mr-ahmad-alkhashem",
  "name": "Mr Ahmad Alkhashem",
  "title": "Senior Lecturer in Arabic",
  "department": "School of Languages, Cultures and Linguistics",
  "expertise_topics": [],
  "biography": "School of Languages, Cultures and Linguistics Mr Ahmad Alkhashem You are here: Home About You are viewing: Key information Show all jumplinks Jump to: Key information Jump to: Contact Key information Roles School of Languages, Cultures and Linguistics Senior Lecturer in Arabic Department School of Languages, Cultures and Linguistics Building Russell Square: College Buildings Office 434 Email address aa40@soas. ac. uk Telephone number +44(0)20 7898 4208 Contact Ahmad Email aa40@soas. ac. uk Telephone +44(0)20 7898 4208 Related content School of Languages, Cultures and Linguistics BA Japanese BA Japanese at SOAS University of London School of Languages, Cultures and Linguistics BA Africa and Black Diaspora and... BA Africa and Black Diaspora and... at SOAS University of London School of Languag",
  "research_interests": null,
  "publications": "https://www.soas.ac.uk/; https://www.soas.ac.uk/about; https://www.soas.ac.uk/about/colleges-schools-and-departments/college-humanities/school-languages-cultures-and-linguistics; https://www.soas.ac.uk/study/find-course/ba-africa-and-black-diaspora-and; https://www.soas.ac.uk/study/find-course/ba-japanese; https://www.soas.ac.uk/study/find-course/ba-korean; mailto:aa40@soas.ac.uk",
  "languages": [
    "Arabic",
    "Japanese",
    "Korean"
  ],
  "source_url": "https://www.soas.ac.uk/about/ahmad-alkhashem",
  "last_checked": "2026-02-21",
  "content_hash": "5655805aa06f94e14731f7a443034246f16802b13e1aaad0769d5c77f2512cf4",
  "email_contact": "aa40@soas.ac.uk"
}